molecule_docker/__init__.py
molecule_docker/driver.py
molecule_docker/cookiecutter/cookiecutter.json
molecule_docker/cookiecutter/{{cookiecutter.molecule_directory}}/{{cookiecutter.scenario_name}}/converge.yml
molecule_docker/playbooks/Dockerfile.j2
molecule_docker/playbooks/create.yml
molecule_docker/playbooks/destroy.yml
molecule_docker/playbooks/validate-dockerfile.yml
molecule_docker/playbooks/filter_plugins/get_docker_networks.py
molecule_docker/playbooks/tasks/create_network.yml
molecule_docker/playbooks/tasks/delete_network.yml
molecule_docker/test/__init__.py
molecule_docker/test/conftest.py
molecule_docker/test/test_driver.py
molecule_docker/test/test_func.py
molecule_docker/test/scenarios/with-context/molecule/default/Dockerfile.j2
molecule_docker/test/scenarios/with-context/molecule/default/FOO
molecule_docker/test/scenarios/with-context/molecule/default/converge.yml
molecule_docker/test/scenarios/with-context/molecule/default/molecule.yml
molecule_docker-2.1.0.dist-info/LICENSE
molecule_docker-2.1.0.dist-info/METADATA
molecule_docker-2.1.0.dist-info/WHEEL
molecule_docker-2.1.0.dist-info/entry_points.txt
molecule_docker-2.1.0.dist-info/top_level.txt
molecule_docker-2.1.0.dist-info/RECORD
