Metadata-Version: 2.1
Name: molecule-docker
Version: 2.1.0
Summary: Molecule aids in the development and testing of Ansible roles
Home-page: https://github.com/ansible-community/molecule-docker
Author: Ansible by Red Hat
Author-email: info@ansible.com
Maintainer: Ansible by Red Hat
Maintainer-email: info@ansible.com
License: MIT
Project-URL: Bug Tracker, https://github.com/ansible-community/molecule-docker/issues
Project-URL: Release Management, https://github.com/ansible-community/molecule-docker/releases
Project-URL: CI, https://github.com/ansible-community/molecule-docker/actions
Project-URL: Code of Conduct, https://docs.ansible.com/ansible/latest/community/code_of_conduct.html
Project-URL: Documentation, https://molecule.readthedocs.io
Project-URL: Discussions, https://github.com/ansible-community/molecule/discussions
Project-URL: Source Code, https://github.com/ansible-community/molecule-docker
Keywords: ansible,docker,testing,molecule
Classifier: Development Status :: 5 - Production/Stable
Classifier: Environment :: Console
Classifier: Intended Audience :: Developers
Classifier: Intended Audience :: Information Technology
Classifier: Intended Audience :: System Administrators
Classifier: License :: OSI Approved :: MIT License
Classifier: Natural Language :: English
Classifier: Operating System :: OS Independent
Classifier: Programming Language :: Python :: 3
Classifier: Programming Language :: Python :: 3.8
Classifier: Programming Language :: Python :: 3.9
Classifier: Programming Language :: Python :: 3.10
Classifier: Programming Language :: Python :: 3.11
Classifier: Topic :: System :: Systems Administration
Classifier: Topic :: Utilities
Requires-Python: >=3.8
Provides-Extra: docs
Provides-Extra: lint
Provides-Extra: test
License-File: LICENSE
